{"stocks": [{"ticker": "NVDA", "name": "NVIDIA Corporation", "price": 227.9, "change": -7.84, "changePercent": -3.33, "change5dPercent": 5.9, "marketCap": 5523732923681, "volume": 95275865, "avgVolume10d": 147652466, "avgVolume60d": 170168056, "avgVolume90d": 169899021, "avgTradingValue": 31482726198, "sma10": 215.92, "sma20": 210.43, "sma30": 203.46, "sma50": 193.12, "sma100": 189.62, "sma200": 185.97, "sector": "Technology", "indices": []}, {"ticker": "GOOGL", "name": "Alphabet Inc.", "price": 396.12, "change": -4.95, "changePercent": -1.23, "change5dPercent": -1.17, "marketCap": 4808256262240, "volume": 10029162, "avgVolume10d": 24342976, "avgVolume60d": 28841684, "avgVolume90d": 31626994, "avgTradingValue": 10186296537, "sma10": 394.43, "sma20": 372.86, "sma30": 356.16, "sma50": 332.72, "sma100": 326.25, "sma200": 291.06, "sector": "Communication Services", "indices": []}, {"ticker": "GOOG", "name": "Alphabet Inc.", "price": 392.29, "change": -4.88, "changePercent": -1.23, "change5dPercent": -1.2, "marketCap": 4762581170884, "volume": 7962823, "avgVolume10d": 15904592, "avgVolume60d": 19225557, "avgVolume90d": 20645474, "avgTradingValue": 6724785422, "sma10": 391.05, "sma20": 370.13, "sma30": 353.58, "sma50": 330.76, "sma100": 325.49, "sma200": 291.0, "sector": "Communication Services", "indices": []}, {"ticker": "AAPL", "name": "AAPL", "price": 302.07, "change": 3.86, "changePercent": 1.29, "change5dPercent": 3.08, "marketCap": 4438959765240, "volume": 25155177, "avgVolume10d": 45333157, "avgVolume60d": 43427339, "avgVolume90d": 47043578, "avgTradingValue": 13184388789, "sma10": 291.46, "sma20": 281.45, "sma30": 274.56, "sma50": 266.01, "sma100": 265.08, "sma200": 258.66, "sector": "", "indices": []}, {"ticker": "AMZN", "name": "AMZN", "price": 262.15, "change": -5.07, "changePercent": -1.9, "change5dPercent": -3.86, "marketCap": 2819868825127, "volume": 23425731, "avgVolume10d": 37547633, "avgVolume60d": 46187747, "avgVolume90d": 49050182, "avgTradingValue": 11877540480, "sma10": 269.87, "sma20": 264.43, "sma30": 254.87, "sma50": 236.67, "sma100": 231.18, "sma200": 229.41, "sector": "", "indices": []}, {"ticker": "AVGO", "name": "AVGO", "price": 429.13, "change": -10.66, "changePercent": -2.42, "change5dPercent": -0.2, "marketCap": 2028615889659, "volume": 8852442, "avgVolume10d": 18371274, "avgVolume60d": 24032192, "avgVolume90d": 24506819, "avgTradingValue": 7854366777, "sma10": 424.53, "sma20": 418.73, "sma30": 402.08, "sma50": 369.33, "sma100": 351.58, "sma200": 345.85, "sector": "", "indices": []}, {"ticker": "WMT", "name": "Walmart Inc.", "price": 131.36, "change": -1.1, "changePercent": -0.83, "change5dPercent": 0.71, "marketCap": 1048225146595, "volume": 8711873, "avgVolume10d": 14078937, "avgVolume60d": 18450296, "avgVolume90d": 26178529, "avgTradingValue": 1993714494, "sma10": 130.41, "sma20": 129.89, "sma30": 128.48, "sma50": 126.36, "sma100": 123.46, "sma200": 113.57, "sector": "Consumer Defensive", "indices": []}, {"ticker": "MU", "name": "Micron Technology, Inc.", "price": 736.49, "change": -39.52, "changePercent": -5.09, "change5dPercent": -1.38, "marketCap": 833846584841, "volume": 31333798, "avgVolume10d": 55156099, "avgVolume60d": 44443194, "avgVolume90d": 42023537, "avgTradingValue": 29293942446, "sma10": 715.47, "sma20": 606.26, "sma30": 546.33, "sma50": 486.42, "sma100": 430.05, "sma200": 307.04, "sector": "Technology", "indices": []}, {"ticker": "AMD", "name": "AMD", "price": 430.84, "change": -18.86, "changePercent": -4.19, "change5dPercent": -5.35, "marketCap": 703286196661, "volume": 15773173, "avgVolume10d": 45447177, "avgVolume60d": 38935366, "avgVolume90d": 39463107, "avgTradingValue": 17036777761, "sma10": 421.5, "sma20": 372.05, "sma30": 330.43, "sma50": 279.35, "sma100": 248.7, "sma200": 224.22, "sector": "", "indices": []}, {"ticker": "ASML", "name": "ASML", "price": 1518.49, "change": -66.02, "changePercent": -4.17, "change5dPercent": -4.62, "marketCap": 585006193410, "volume": 1091292, "avgVolume10d": 1793519, "avgVolume60d": 1717744, "avgVolume90d": 1807542, "avgTradingValue": 2455657586, "sma10": 1525.38, "sma20": 1478.49, "sma30": 1462.26, "sma50": 1415.54, "sma100": 1373.42, "sma200": 1152.72, "sector": "", "indices": []}, {"ticker": "INTC", "name": "Intel Corporation", "price": 107.88, "change": -8.05, "changePercent": -6.94, "change5dPercent": -13.64, "marketCap": 543360863067, "volume": 83633052, "avgVolume10d": 149405365, "avgVolume60d": 114752189, "avgVolume90d": 120210669, "avgTradingValue": 15297781620, "sma10": 114.56, "sma20": 97.53, "sma30": 85.61, "sma50": 69.48, "sma100": 57.19, "sma200": 44.78, "sector": "Technology", "indices": []}, {"ticker": "COST", "name": "COST", "price": 1044.31, "change": 3.06, "changePercent": 0.29, "change5dPercent": 3.52, "marketCap": 464466516244, "volume": 943378, "avgVolume10d": 1777357, "avgVolume60d": 1798512, "avgVolume90d": 2058016, "avgTradingValue": 1695568416, "sma10": 1018.58, "sma20": 1011.12, "sma30": 1007.6, "sma50": 1000.23, "sma100": 976.0, "sma200": 951.94, "sector": "", "indices": []}, {"ticker": "CSCO", "name": "CSCO", "price": 116.78, "change": 1.25, "changePercent": 1.08, "change5dPercent": 20.92, "marketCap": 462572368318, "volume": 18273046, "avgVolume10d": 28993794, "avgVolume60d": 22539719, "avgVolume90d": 23320863, "avgTradingValue": 2278310402, "sma10": 99.95, "sma20": 94.62, "sma30": 90.69, "sma50": 85.73, "sma100": 81.65, "sma200": 76.01, "sector": "", "indices": []}, {"ticker": "CAT", "name": "CAT", "price": 886.8, "change": -33.42, "changePercent": -3.63, "change5dPercent": -1.19, "marketCap": 408273327281, "volume": 1448987, "avgVolume10d": 2390958, "avgVolume60d": 2503651, "avgVolume90d": 2672426, "avgTradingValue": 2101131652, "sma10": 904.77, "sma20": 867.9, "sma30": 835.39, "sma50": 781.28, "sma100": 727.03, "sma200": 612.96, "sector": "", "indices": []}, {"ticker": "LRCX", "name": "Lam Research Corporation", "price": 284.9, "change": -14.25, "changePercent": -4.76, "change5dPercent": -3.11, "marketCap": 356541155971, "volume": 5392955, "avgVolume10d": 9077245, "avgVolume60d": 9916080, "avgVolume90d": 10830226, "avgTradingValue": 2549342379, "sma10": 287.69, "sma20": 273.22, "sma30": 267.06, "sma50": 247.87, "sma100": 233.05, "sma200": 183.41, "sector": "Technology", "indices": []}, {"ticker": "KO", "name": "Coca-Cola Company (The)", "price": 80.76, "change": 0.32, "changePercent": 0.39, "change5dPercent": 2.99, "marketCap": 347705127114, "volume": 8774492, "avgVolume10d": 12996459, "avgVolume60d": 15278758, "avgVolume90d": 16804873, "avgTradingValue": 1085590727, "sma10": 79.29, "sma20": 78.03, "sma30": 77.51, "sma50": 77.0, "sma100": 75.52, "sma200": 71.79, "sector": "Consumer Defensive", "indices": []}, {"ticker": "AMAT", "name": "AMAT", "price": 438.79, "change": -1.77, "changePercent": -0.4, "change5dPercent": 0.77, "marketCap": 346521823952, "volume": 7236390, "avgVolume10d": 8193199, "avgVolume60d": 6706811, "avgVolume90d": 7280128, "avgTradingValue": 2902726798, "sma10": 426.77, "sma20": 411.51, "sma30": 403.09, "sma50": 380.85, "sma100": 351.21, "sma200": 280.82, "sector": "", "indices": []}, {"ticker": "TXN", "name": "Texas Instruments Incorporated", "price": 305.68, "change": -2.49, "changePercent": -0.81, "change5dPercent": 6.21, "marketCap": 278451982557, "volume": 2482457, "avgVolume10d": 7047705, "avgVolume60d": 7126404, "avgVolume90d": 7669617, "avgTradingValue": 2435362679, "sma10": 293.61, "sma20": 277.56, "sma30": 256.1, "sma50": 230.4, "sma100": 215.57, "sma200": 195.55, "sector": "Technology", "indices": []}, {"ticker": "SNDK", "name": "Sandisk Corporation", "price": 1395.15, "change": 12.43, "changePercent": 0.9, "change5dPercent": -10.7, "marketCap": 207466339239, "volume": 9522230, "avgVolume10d": 16238113, "avgVolume60d": 17462773, "avgVolume90d": 18431565, "avgTradingValue": 18648411447, "sma10": 1419.91, "sma20": 1216.87, "sma30": 1096.2, "sma50": 922.4, "sma100": 704.46, "sma200": 421.88, "sector": "Technology", "indices": []}, {"ticker": "ADI", "name": "ADI", "price": 420.39, "change": -6.4, "changePercent": -1.5, "change5dPercent": 0.93, "marketCap": 205631596887, "volume": 1366415, "avgVolume10d": 3315131, "avgVolume60d": 3621603, "avgVolume90d": 3792485, "avgTradingValue": 1360519089, "sma10": 416.44, "sma20": 403.54, "sma30": 384.83, "sma50": 356.44, "sma100": 334.76, "sma200": 289.16, "sector": "", "indices": []}, {"ticker": "STX", "name": "Seagate Technology Holdings PLC", "price": 791.35, "change": -13.41, "changePercent": -1.67, "change5dPercent": 1.11, "marketCap": 177982884639, "volume": 1277524, "avgVolume10d": 4391582, "avgVolume60d": 3951923, "avgVolume90d": 4235866, "avgTradingValue": 3267742954, "sma10": 790.13, "sma20": 698.67, "sma30": 634.72, "sma50": 539.36, "sma100": 451.01, "sma200": 337.11, "sector": "Technology", "indices": []}, {"ticker": "GLW", "name": "Corning Incorporated", "price": 194.89, "change": -13.39, "changePercent": -6.43, "change5dPercent": 4.25, "marketCap": 167876012043, "volume": 9747664, "avgVolume10d": 17636036, "avgVolume60d": 13368152, "avgVolume90d": 12074566, "avgTradingValue": 2520694660, "sma10": 188.83, "sma20": 176.44, "sma30": 172.55, "sma50": 157.03, "sma100": 134.37, "sma200": 106.64, "sector": "Technology", "indices": []}, {"ticker": "WDC", "name": "Western Digital Corporation", "price": 479.68, "change": -9.47, "changePercent": -1.94, "change5dPercent": -0.07, "marketCap": 165404337613, "volume": 3592551, "avgVolume10d": 7609415, "avgVolume60d": 8322419, "avgVolume90d": 9107599, "avgTradingValue": 3490609593, "sma10": 480.22, "sma20": 441.34, "sma30": 409.29, "sma50": 358.5, "sma100": 300.34, "sma200": 211.49, "sector": "Technology", "indices": []}, {"ticker": "UNP", "name": "Union Pacific Corporation", "price": 268.93, "change": -0.41, "changePercent": -0.15, "change5dPercent": 1.62, "marketCap": 159673232953, "volume": 1357185, "avgVolume10d": 2270708, "avgVolume60d": 2908608, "avgVolume90d": 3255910, "avgTradingValue": 776163709, "sma10": 265.71, "sma20": 264.35, "sma30": 259.44, "sma50": 252.72, "sma100": 247.87, "sma200": 235.38, "sector": "Industrials", "indices": []}, {"ticker": "DELL", "name": "DELL", "price": 241.87, "change": -6.02, "changePercent": -2.43, "change5dPercent": -7.14, "marketCap": 157072592168, "volume": 1752158, "avgVolume10d": 6607055, "avgVolume60d": 8200224, "avgVolume90d": 8038299, "avgTradingValue": 1360403815, "sma10": 237.71, "sma20": 224.13, "sma30": 210.46, "sma50": 190.17, "sma100": 156.39, "sma200": 146.32, "sector": "", "indices": []}, {"ticker": "MRVL", "name": "Marvell Technology, Inc.", "price": 177.98, "change": -4.6, "changePercent": -2.52, "change5dPercent": 4.61, "marketCap": 156575175530, "volume": 12336660, "avgVolume10d": 22542356, "avgVolume60d": 24588706, "avgVolume90d": 20948429, "avgTradingValue": 4209143509, "sma10": 170.85, "sma20": 164.65, "sma30": 151.58, "sma50": 128.19, "sma100": 104.83, "sma200": 93.15, "sector": "Technology", "indices": []}, {"ticker": "WELL", "name": "Welltower Inc.", "price": 215.1, "change": -2.65, "changePercent": -1.22, "change5dPercent": 0.56, "marketCap": 151898666180, "volume": 1318396, "avgVolume10d": 2758679, "avgVolume60d": 2916563, "avgVolume90d": 3054636, "avgTradingValue": 604477674, "sma10": 215.57, "sma20": 212.58, "sma30": 210.67, "sma50": 207.07, "sma100": 200.12, "sma200": 188.45, "sector": "Real Estate", "indices": []}, {"ticker": "VRT", "name": "Vertiv Holdings, LLC", "price": 370.26, "change": -5.97, "changePercent": -1.59, "change5dPercent": 8.91, "marketCap": 142276821897, "volume": 2483153, "avgVolume10d": 4988975, "avgVolume60d": 7504395, "avgVolume90d": 7001081, "avgTradingValue": 1881773781, "sma10": 356.24, "sma20": 336.5, "sma30": 320.93, "sma50": 296.62, "sma100": 248.46, "sma200": 203.05, "sector": "Industrials", "indices": []}, {"ticker": "PLD", "name": "Prologis, Inc.", "price": 141.1, "change": -1.56, "changePercent": -1.09, "change5dPercent": -2.07, "marketCap": 131869888996, "volume": 859079, "avgVolume10d": 2671827, "avgVolume60d": 3426949, "avgVolume90d": 3470796, "avgTradingValue": 437790229, "sma10": 142.19, "sma20": 141.93, "sma30": 140.64, "sma50": 137.02, "sma100": 134.75, "sma200": 125.52, "sector": "Real Estate", "indices": []}, {"ticker": "CVS", "name": "CVS", "price": 96.5, "change": -0.65, "changePercent": -0.67, "change5dPercent": 6.57, "marketCap": 123114223126, "volume": 3444820, "avgVolume10d": 9854072, "avgVolume60d": 8112400, "avgVolume90d": 8659182, "avgTradingValue": 732315503, "sma10": 90.66, "sma20": 85.02, "sma30": 82.23, "sma50": 78.54, "sma100": 78.06, "sma200": 75.92, "sector": "", "indices": []}, {"ticker": "MO", "name": "Altria Group, Inc.", "price": 72.64, "change": 0.23, "changePercent": 0.32, "change5dPercent": 6.64, "marketCap": 121426135037, "volume": 3883113, "avgVolume10d": 8905441, "avgVolume60d": 9431630, "avgVolume90d": 9846474, "avgTradingValue": 672050682, "sma10": 70.86, "sma20": 69.31, "sma30": 68.22, "sma50": 67.04, "sma100": 64.41, "sma200": 62.34, "sector": "Consumer Defensive", "indices": []}, {"ticker": "SBUX", "name": "Starbucks Corporation", "price": 106.21, "change": -0.19, "changePercent": -0.18, "change5dPercent": 1.22, "marketCap": 121024745782, "volume": 3178389, "avgVolume10d": 6894998, "avgVolume60d": 7713518, "avgVolume90d": 8568602, "avgTradingValue": 794587868, "sma10": 105.64, "sma20": 103.14, "sma30": 101.21, "sma50": 98.53, "sma100": 95.61, "sma200": 90.05, "sector": "Consumer Cyclical", "indices": []}, {"ticker": "ENB", "name": "ENB", "price": 55.15, "change": -1.07, "changePercent": -1.9, "change5dPercent": 2.91, "marketCap": 120452693918, "volume": 1938345, "avgVolume10d": 4959944, "avgVolume60d": 4582207, "avgVolume90d": 5041652, "avgTradingValue": 232031612, "sma10": 54.73, "sma20": 53.91, "sma30": 53.8, "sma50": 53.89, "sma100": 51.38, "sma200": 49.3, "sector": "", "indices": []}, {"ticker": "PWR", "name": "Quanta Services, Inc.", "price": 767.35, "change": -12.73, "changePercent": -1.63, "change5dPercent": 3.0, "marketCap": 115225183812, "volume": 569015, "avgVolume10d": 1233351, "avgVolume60d": 1123431, "avgVolume90d": 1123753, "avgTradingValue": 843881957, "sma10": 767.83, "sma20": 706.4, "sma30": 665.1, "sma50": 623.73, "sma100": 554.97, "sma200": 485.94, "sector": "Industrials", "indices": []}, {"ticker": "HWM", "name": "Howmet Aerospace Inc.", "price": 262.8, "change": -9.57, "changePercent": -3.51, "change5dPercent": -2.87, "marketCap": 105484342679, "volume": 1003756, "avgVolume10d": 2736075, "avgVolume60d": 2332362, "avgVolume90d": 2549633, "avgTradingValue": 645344068, "sma10": 263.31, "sma20": 253.3, "sma30": 252.19, "sma50": 246.84, "sma100": 237.07, "sma200": 213.76, "sector": "Industrials", "indices": []}, {"ticker": "EQNR", "name": "Equinor ASA", "price": 39.01, "change": 0.5, "changePercent": 1.3, "change5dPercent": 6.32, "marketCap": 97248131046, "volume": 1419262, "avgVolume10d": 3788886, "avgVolume60d": 7283957, "avgVolume90d": 6753867, "avgTradingValue": 152568025, "sma10": 38.68, "sma20": 38.61, "sma30": 38.69, "sma50": 38.49, "sma100": 32.32, "sma200": 27.87, "sector": "Energy", "indices": []}, {"ticker": "WMB", "name": "Williams Companies, Inc. (The)", "price": 77.82, "change": 0.12, "changePercent": 0.16, "change5dPercent": 8.14, "marketCap": 95185957204, "volume": 3623414, "avgVolume10d": 6474071, "avgVolume60d": 6239786, "avgVolume90d": 6888622, "avgTradingValue": 448992508, "sma10": 75.03, "sma20": 73.82, "sma30": 73.25, "sma50": 73.25, "sma100": 69.56, "sma200": 64.18, "sector": "Energy", "indices": []}, {"ticker": "FTNT", "name": "Fortinet, Inc.", "price": 122.36, "change": 0.5, "changePercent": 0.41, "change5dPercent": 7.26, "marketCap": 89375775652, "volume": 1925100, "avgVolume10d": 7005290, "avgVolume60d": 6158546, "avgVolume90d": 6527455, "avgTradingValue": 578124198, "sma10": 108.24, "sma20": 96.63, "sma30": 91.36, "sma50": 87.68, "sma100": 83.97, "sma200": 83.3, "sector": "Technology", "indices": []}, {"ticker": "JCI", "name": "Johnson Controls International ", "price": 141.97, "change": -3.06, "changePercent": -2.11, "change5dPercent": 1.76, "marketCap": 86749285523, "volume": 1072791, "avgVolume10d": 3800359, "avgVolume60d": 3723704, "avgVolume90d": 4403336, "avgTradingValue": 450535321, "sma10": 142.47, "sma20": 142.32, "sma30": 141.24, "sma50": 137.73, "sma100": 132.09, "sma200": 121.32, "sector": "Industrials", "indices": []}, {"ticker": "EPD", "name": "Enterprise Products Partners L.", "price": 39.44, "change": 0.22, "changePercent": 0.55, "change5dPercent": 6.06, "marketCap": 85448151802, "volume": 1239277, "avgVolume10d": 4337217, "avgVolume60d": 4432966, "avgVolume90d": 4725724, "avgTradingValue": 182737098, "sma10": 38.27, "sma20": 37.91, "sma30": 37.6, "sma50": 37.44, "sma100": 35.38, "sma200": 32.83, "sector": "Energy", "indices": []}, {"ticker": "CSX", "name": "CSX", "price": 45.73, "change": -0.19, "changePercent": -0.41, "change5dPercent": 2.01, "marketCap": 84898361778, "volume": 3810370, "avgVolume10d": 12113657, "avgVolume60d": 12677129, "avgVolume90d": 13329633, "avgTradingValue": 565624434, "sma10": 45.0, "sma20": 44.88, "sma30": 44.02, "sma50": 42.35, "sma100": 40.44, "sma200": 37.6, "sector": "", "indices": []}, {"ticker": "SU", "name": "Suncor Energy  Inc.", "price": 67.63, "change": 0.84, "changePercent": 1.26, "change5dPercent": 5.66, "marketCap": 79971875614, "volume": 1830793, "avgVolume10d": 3396929, "avgVolume60d": 4629449, "avgVolume90d": 4886099, "avgTradingValue": 204903038, "sma10": 66.25, "sma20": 65.57, "sma30": 65.1, "sma50": 63.99, "sma100": 57.42, "sma200": 49.27, "sector": "Energy", "indices": []}, {"ticker": "CIEN", "name": "CIEN", "price": 559.84, "change": -31.73, "changePercent": -5.36, "change5dPercent": 2.14, "marketCap": 79046665840, "volume": 961777, "avgVolume10d": 1746327, "avgVolume60d": 2735619, "avgVolume90d": 3063528, "avgTradingValue": 1027035721, "sma10": 563.49, "sma20": 534.9, "sma30": 516.1, "sma50": 460.88, "sma100": 366.74, "sma200": 260.88, "sector": "", "indices": []}, {"ticker": "COHR", "name": "COHR", "price": 388.47, "change": -16.47, "changePercent": -4.07, "change5dPercent": 15.87, "marketCap": 76028802691, "volume": 3949471, "avgVolume10d": 7377297, "avgVolume60d": 7643872, "avgVolume90d": 6933623, "avgTradingValue": 2227743321, "sma10": 361.56, "sma20": 345.54, "sma30": 329.84, "sma50": 298.18, "sma100": 256.96, "sma200": 191.5, "sector": "", "indices": []}, {"ticker": "LITE", "name": "Lumentum Holdings Inc.", "price": 970.99, "change": -30.82, "changePercent": -3.08, "change5dPercent": 7.43, "marketCap": 75567917810, "volume": 3071249, "avgVolume10d": 6405914, "avgVolume60d": 6411594, "avgVolume90d": 5997767, "avgTradingValue": 5272878216, "sma10": 976.0, "sma20": 922.79, "sma30": 902.15, "sma50": 818.97, "sma100": 648.44, "sma200": 422.58, "sector": "Technology", "indices": []}, {"ticker": "MPC", "name": "Marathon Petroleum Corporation", "price": 254.12, "change": 5.3, "changePercent": 2.13, "change5dPercent": 3.78, "marketCap": 74169420775, "volume": 747235, "avgVolume10d": 2452713, "avgVolume60d": 2597273, "avgVolume90d": 2488451, "avgTradingValue": 532768969, "sma10": 250.25, "sma20": 240.01, "sma30": 235.91, "sma50": 235.33, "sma100": 209.91, "sma200": 196.01, "sector": "Energy", "indices": []}, {"ticker": "VLO", "name": "Valero Energy Corporation", "price": 248.73, "change": 3.96, "changePercent": 1.62, "change5dPercent": 3.18, "marketCap": 73839760470, "volume": 858282, "avgVolume10d": 2907728, "avgVolume60d": 3687994, "avgVolume90d": 3577093, "avgTradingValue": 676981645, "sma10": 245.2, "sma20": 242.25, "sma30": 241.12, "sma50": 239.53, "sma100": 214.12, "sma200": 187.09, "sector": "Energy", "indices": []}, {"ticker": "RKLB", "name": "Rocket Lab Corporation", "price": 123.42, "change": -9.13, "changePercent": -6.89, "change5dPercent": 17.02, "marketCap": 71507578746, "volume": 13707948, "avgVolume10d": 31049434, "avgVolume60d": 23593547, "avgVolume90d": 23020444, "avgTradingValue": 2537500102, "sma10": 104.28, "sma20": 93.62, "sma30": 86.48, "sma50": 79.22, "sma100": 78.4, "sma200": 64.93, "sector": "Industrials", "indices": []}, {"ticker": "KEYS", "name": "Keysight Technologies Inc.", "price": 349.6, "change": -11.95, "changePercent": -3.31, "change5dPercent": -2.97, "marketCap": 60025873250, "volume": 858545, "avgVolume10d": 1131974, "avgVolume60d": 1503502, "avgVolume90d": 1367476, "avgTradingValue": 401262501, "sma10": 358.97, "sma20": 350.36, "sma30": 340.58, "sma50": 318.06, "sma100": 275.16, "sma200": 225.83, "sector": "Technology", "indices": []}, {"ticker": "TRGP", "name": "Targa Resources, Inc.", "price": 270.5, "change": 3.02, "changePercent": 1.13, "change5dPercent": 9.02, "marketCap": 58096593839, "volume": 916016, "avgVolume10d": 1209331, "avgVolume60d": 1421966, "avgVolume90d": 1406800, "avgTradingValue": 296700369, "sma10": 257.84, "sma20": 250.22, "sma30": 247.15, "sma50": 244.42, "sma100": 223.22, "sma200": 193.45, "sector": "Energy", "indices": []}, {"ticker": "OKE", "name": "ONEOK, Inc.", "price": 91.55, "change": 0.52, "changePercent": 0.57, "change5dPercent": 7.5, "marketCap": 57723611630, "volume": 1315093, "avgVolume10d": 3913029, "avgVolume60d": 4904601, "avgVolume90d": 4832377, "avgTradingValue": 361987859, "sma10": 88.49, "sma20": 87.67, "sma30": 86.82, "sma50": 87.05, "sma100": 82.21, "sma200": 75.9, "sector": "Energy", "indices": []}, {"ticker": "FANG", "name": "Diamondback Energy, Inc.", "price": 202.91, "change": 2.65, "changePercent": 1.32, "change5dPercent": 8.12, "marketCap": 57078466244, "volume": 626154, "avgVolume10d": 2501005, "avgVolume60d": 3339762, "avgVolume90d": 2917491, "avgTradingValue": 470159600, "sma10": 198.4, "sma20": 197.29, "sma30": 193.82, "sma50": 191.67, "sma100": 174.94, "sma200": 158.78, "sector": "Energy", "indices": []}, {"ticker": "CVE", "name": "CVE", "price": 30.48, "change": 0.33, "changePercent": 1.08, "change5dPercent": 7.31, "marketCap": 56942247880, "volume": 2948335, "avgVolume10d": 8648753, "avgVolume60d": 12812407, "avgVolume90d": 13100577, "avgTradingValue": 230352447, "sma10": 29.57, "sma20": 28.32, "sma30": 27.53, "sma50": 26.38, "sma100": 22.9, "sma200": 19.85, "sector": "", "indices": []}, {"ticker": "ALL", "name": "ALL", "price": 217.85, "change": 1.4, "changePercent": 0.65, "change5dPercent": 2.21, "marketCap": 56169222572, "volume": 587340, "avgVolume10d": 1614004, "avgVolume60d": 1416077, "avgVolume90d": 1604948, "avgTradingValue": 320671917, "sma10": 216.22, "sma20": 215.7, "sma30": 214.96, "sma50": 211.55, "sma100": 207.79, "sma200": 205.2, "sector": "", "indices": []}, {"ticker": "NBIS", "name": "Nebius Group N.V.", "price": 212.99, "change": -8.16, "changePercent": -3.69, "change5dPercent": 20.3, "marketCap": 54286685088, "volume": 13887827, "avgVolume10d": 19613592, "avgVolume60d": 16867463, "avgVolume90d": 15882470, "avgTradingValue": 2970645709, "sma10": 191.59, "sma20": 170.32, "sma30": 161.61, "sma50": 140.47, "sma100": 117.65, "sma200": 105.82, "sector": "Communication Services", "indices": []}, {"ticker": "CARR", "name": "CARR", "price": 64.55, "change": -2.18, "changePercent": -3.27, "change5dPercent": -3.41, "marketCap": 53697025614, "volume": 1450431, "avgVolume10d": 5033053, "avgVolume60d": 6470427, "avgVolume90d": 7219615, "avgTradingValue": 389742825, "sma10": 66.03, "sma20": 64.25, "sma30": 62.85, "sma50": 60.47, "sma100": 59.64, "sma200": 59.19, "sector": "", "indices": []}, {"ticker": "NUE", "name": "Nucor Corporation", "price": 226.82, "change": -6.03, "changePercent": -2.59, "change5dPercent": -0.3, "marketCap": 51811066125, "volume": 539459, "avgVolume10d": 1247215, "avgVolume60d": 1505444, "avgVolume90d": 1634086, "avgTradingValue": 350836651, "sma10": 230.01, "sma20": 223.29, "sma30": 210.6, "sma50": 192.45, "sma100": 184.06, "sma200": 164.24, "sector": "Basic Materials", "indices": []}, {"ticker": "MCHP", "name": "Microchip Technology Incorporat", "price": 94.95, "change": -2.09, "changePercent": -2.15, "change5dPercent": -4.18, "marketCap": 51397047617, "volume": 2788706, "avgVolume10d": 12296600, "avgVolume60d": 9561736, "avgVolume90d": 9622784, "avgTradingValue": 1090216124, "sma10": 98.28, "sma20": 92.74, "sma30": 86.04, "sma50": 77.26, "sma100": 75.37, "sma200": 68.75, "sector": "Technology", "indices": []}, {"ticker": "EBAY", "name": "EBAY", "price": 115.38, "change": 2.14, "changePercent": 1.89, "change5dPercent": 7.14, "marketCap": 51308638916, "volume": 1980665, "avgVolume10d": 7380706, "avgVolume60d": 5727492, "avgVolume90d": 5620698, "avgTradingValue": 760076653, "sma10": 109.7, "sma20": 106.43, "sma30": 103.84, "sma50": 98.67, "sma100": 93.68, "sma200": 91.34, "sector": "", "indices": []}, {"ticker": "FLEX", "name": "Flex Ltd.", "price": 139.29, "change": -4.31, "changePercent": -3.0, "change5dPercent": -2.03, "marketCap": 51132415303, "volume": 1960657, "avgVolume10d": 8265455, "avgVolume60d": 4311664, "avgVolume90d": 4191527, "avgTradingValue": 720602115, "sma10": 130.96, "sma20": 109.69, "sma30": 98.45, "sma50": 84.86, "sma100": 74.3, "sma200": 66.31, "sector": "Technology", "indices": []}, {"ticker": "ON", "name": "ON Semiconductor Corporation", "price": 114.45, "change": -3.92, "changePercent": -3.31, "change5dPercent": 10.9, "marketCap": 44444091813, "volume": 4641971, "avgVolume10d": 14894087, "avgVolume60d": 9618517, "avgVolume90d": 9711906, "avgTradingValue": 1362638250, "sma10": 107.42, "sma20": 101.29, "sma30": 91.24, "sma50": 78.69, "sma100": 70.74, "sma200": 60.59, "sector": "Technology", "indices": []}, {"ticker": "HPE", "name": "Hewlett Packard Enterprise Comp", "price": 32.93, "change": -1.2, "changePercent": -3.52, "change5dPercent": 5.04, "marketCap": 43733109558, "volume": 7078846, "avgVolume10d": 16438574, "avgVolume60d": 17381122, "avgVolume90d": 17441247, "avgTradingValue": 457668380, "sma10": 31.04, "sma20": 29.69, "sma30": 28.13, "sma50": 25.91, "sma100": 24.06, "sma200": 23.45, "sector": "Technology", "indices": []}, {"ticker": "VTR", "name": "Ventas, Inc.", "price": 88.17, "change": -1.79, "changePercent": -1.99, "change5dPercent": 1.04, "marketCap": 42938509786, "volume": 892079, "avgVolume10d": 4765497, "avgVolume60d": 3791082, "avgVolume90d": 3540904, "avgTradingValue": 441353995, "sma10": 87.97, "sma20": 86.43, "sma30": 85.81, "sma50": 85.04, "sma100": 82.49, "sma200": 76.74, "sector": "Real Estate", "indices": []}, {"ticker": "ERIC", "name": "Ericsson", "price": 12.41, "change": -0.26, "changePercent": -2.05, "change5dPercent": 4.46, "marketCap": 41274761668, "volume": 4323960, "avgVolume10d": 7430226, "avgVolume60d": 9751274, "avgVolume90d": 10039638, "avgTradingValue": 101415059, "sma10": 12.17, "sma20": 11.82, "sma30": 11.82, "sma50": 11.6, "sma100": 10.95, "sma200": 9.76, "sector": "Technology", "indices": []}, {"ticker": "SATS", "name": "EchoStar Corporation", "price": 136.05, "change": 0.94, "changePercent": 0.7, "change5dPercent": 7.0, "marketCap": 39462451647, "volume": 2642541, "avgVolume10d": 4561964, "avgVolume60d": 6119352, "avgVolume90d": 6109794, "avgTradingValue": 616342097, "sma10": 127.61, "sma20": 125.39, "sma30": 126.14, "sma50": 120.7, "sma100": 117.89, "sma200": 92.56, "sector": "Communication Services", "indices": []}, {"ticker": "LYV", "name": "Live Nation Entertainment, Inc.", "price": 168.33, "change": -1.66, "changePercent": -0.98, "change5dPercent": 3.09, "marketCap": 39228398231, "volume": 843327, "avgVolume10d": 3009682, "avgVolume60d": 3070530, "avgVolume90d": 2981415, "avgTradingValue": 420024612, "sma10": 164.71, "sma20": 160.08, "sma30": 160.43, "sma50": 158.35, "sma100": 153.67, "sma200": 152.7, "sector": "Communication Services", "indices": []}, {"ticker": "GFS", "name": "GlobalFoundries Inc.", "price": 71.16, "change": -2.68, "changePercent": -3.63, "change5dPercent": -3.99, "marketCap": 39113060333, "volume": 1517645, "avgVolume10d": 5273254, "avgVolume60d": 4079300, "avgVolume90d": 4110419, "avgTradingValue": 323795048, "sma10": 72.63, "sma20": 67.0, "sma30": 60.8, "sma50": 54.13, "sma100": 48.52, "sma200": 41.58, "sector": "Technology", "indices": []}, {"ticker": "IBKR", "name": "Interactive Brokers Group, Inc.", "price": 87.15, "change": -1.12, "changePercent": -1.27, "change5dPercent": 3.24, "marketCap": 38881909658, "volume": 1760384, "avgVolume10d": 3784428, "avgVolume60d": 4528954, "avgVolume90d": 4830113, "avgTradingValue": 346024480, "sma10": 85.09, "sma20": 81.72, "sma30": 79.3, "sma50": 74.42, "sma100": 73.24, "sma200": 69.41, "sector": "Financial Services", "indices": []}, {"ticker": "ADM", "name": "ADM", "price": 80.39, "change": -1.02, "changePercent": -1.25, "change5dPercent": 3.52, "marketCap": 38699518432, "volume": 1270098, "avgVolume10d": 4399869, "avgVolume60d": 3902758, "avgVolume90d": 3939017, "avgTradingValue": 298529344, "sma10": 79.39, "sma20": 75.4, "sma30": 73.55, "sma50": 72.43, "sma100": 68.59, "sma200": 63.92, "sector": "", "indices": []}, {"ticker": "HAL", "name": "Halliburton Company", "price": 41.33, "change": 0.03, "changePercent": 0.08, "change5dPercent": 3.75, "marketCap": 34572933860, "volume": 2848445, "avgVolume10d": 8534194, "avgVolume60d": 14642287, "avgVolume90d": 14410566, "avgTradingValue": 469892663, "sma10": 40.86, "sma20": 40.47, "sma30": 39.6, "sma50": 38.47, "sma100": 35.64, "sma200": 29.92, "sector": "Energy", "indices": []}, {"ticker": "TSEM", "name": "Tower Semiconductor Ltd.", "price": 275.09, "change": -5.6, "changePercent": -2.0, "change5dPercent": 30.36, "marketCap": 32512965471, "volume": 1120377, "avgVolume10d": 2560957, "avgVolume60d": 2884839, "avgVolume90d": 2637371, "avgTradingValue": 589672059, "sma10": 235.47, "sma20": 221.95, "sma30": 217.05, "sma50": 191.45, "sma100": 159.4, "sma200": 118.91, "sector": "Technology", "indices": []}, {"ticker": "RVMD", "name": "Revolution Medicines, Inc.", "price": 141.4, "change": -8.07, "changePercent": -5.4, "change5dPercent": -0.29, "marketCap": 30076021738, "volume": 640483, "avgVolume10d": 2178118, "avgVolume60d": 2945724, "avgVolume90d": 3430733, "avgTradingValue": 411377242, "sma10": 146.12, "sma20": 143.41, "sma30": 136.1, "sma50": 120.42, "sma100": 110.03, "sma200": 81.75, "sector": "Healthcare", "indices": []}, {"ticker": "ZM", "name": "Zoom Communications, Inc.", "price": 101.38, "change": 3.15, "changePercent": 3.21, "change5dPercent": -7.17, "marketCap": 29898582942, "volume": 2441822, "avgVolume10d": 4562742, "avgVolume60d": 4582563, "avgVolume90d": 4306031, "avgTradingValue": 463121322, "sma10": 105.05, "sma20": 99.22, "sma30": 94.22, "sma50": 87.49, "sma100": 87.1, "sma200": 84.45, "sector": "Technology", "indices": []}, {"ticker": "MTSI", "name": "MACOM Technology Solutions Hold", "price": 382.46, "change": -1.1, "changePercent": -0.29, "change5dPercent": 6.27, "marketCap": 29132778064, "volume": 644465, "avgVolume10d": 1650716, "avgVolume60d": 1194656, "avgVolume90d": 1323956, "avgTradingValue": 422685861, "sma10": 348.57, "sma20": 314.1, "sma30": 294.4, "sma50": 266.17, "sma100": 241.38, "sma200": 193.05, "sector": "Technology", "indices": []}, {"ticker": "EQR", "name": "Equity Residential", "price": 64.41, "change": -0.61, "changePercent": -0.94, "change5dPercent": -1.72, "marketCap": 24155087212, "volume": 711068, "avgVolume10d": 2612836, "avgVolume60d": 2583587, "avgVolume90d": 2674371, "avgTradingValue": 180844258, "sma10": 65.64, "sma20": 64.59, "sma30": 63.37, "sma50": 61.72, "sma100": 61.7, "sma200": 61.32, "sector": "Real Estate", "indices": []}, {"ticker": "TSN", "name": "Tyson Foods, Inc.", "price": 66.31, "change": -0.35, "changePercent": -0.53, "change5dPercent": -3.03, "marketCap": 23365547651, "volume": 592046, "avgVolume10d": 2817244, "avgVolume60d": 2931424, "avgVolume90d": 2948311, "avgTradingValue": 181478208, "sma10": 67.6, "sma20": 65.86, "sma30": 65.44, "sma50": 63.91, "sma100": 62.67, "sma200": 58.33, "sector": "Consumer Defensive", "indices": []}, {"ticker": "RPRX", "name": "Royalty Pharma plc", "price": 52.5, "change": -0.9, "changePercent": -1.69, "change5dPercent": 3.37, "marketCap": 23282972988, "volume": 1702052, "avgVolume10d": 3771085, "avgVolume60d": 3314495, "avgVolume90d": 3499929, "avgTradingValue": 176303532, "sma10": 51.49, "sma20": 50.53, "sma30": 49.78, "sma50": 48.41, "sma100": 45.27, "sma200": 41.07, "sector": "Healthcare", "indices": []}, {"ticker": "AKAM", "name": "AKAM", "price": 150.44, "change": -5.23, "changePercent": -3.36, "change5dPercent": 1.85, "marketCap": 21769290594, "volume": 1806326, "avgVolume10d": 8305422, "avgVolume60d": 5487100, "avgVolume90d": 5034034, "avgTradingValue": 740511704, "sma10": 137.99, "sma20": 118.11, "sma30": 112.48, "sma50": 111.6, "sma100": 103.43, "sma200": 91.29, "sector": "", "indices": []}, {"ticker": "NXT", "name": "Nextpower Inc.", "price": 143.65, "change": 0.9, "changePercent": 0.63, "change5dPercent": 14.09, "marketCap": 21308510517, "volume": 1162870, "avgVolume10d": 2716077, "avgVolume60d": 1963874, "avgVolume90d": 2044370, "avgTradingValue": 271045170, "sma10": 128.75, "sma20": 122.82, "sma30": 119.22, "sma50": 118.38, "sma100": 111.99, "sma200": 95.91, "sector": "Technology", "indices": []}, {"ticker": "ROIV", "name": "Roivant Sciences Ltd.", "price": 28.75, "change": -0.75, "changePercent": -2.56, "change5dPercent": 0.65, "marketCap": 20572829783, "volume": 1176590, "avgVolume10d": 4324059, "avgVolume60d": 5270411, "avgVolume90d": 5812086, "avgTradingValue": 139537099, "sma10": 28.82, "sma20": 28.54, "sma30": 28.59, "sma50": 28.36, "sma100": 26.36, "sma200": 21.49, "sector": "Healthcare", "indices": []}, {"ticker": "MKSI", "name": "MKS Inc.", "price": 299.85, "change": -13.96, "changePercent": -4.45, "change5dPercent": -4.27, "marketCap": 20302751438, "volume": 506847, "avgVolume10d": 1493554, "avgVolume60d": 1236619, "avgVolume90d": 1410210, "avgTradingValue": 382964828, "sma10": 304.93, "sma20": 290.89, "sma30": 281.53, "sma50": 259.61, "sma100": 238.39, "sma200": 184.11, "sector": "Technology", "indices": []}, {"ticker": "DD", "name": "DD", "price": 49.33, "change": -1.27, "changePercent": -2.51, "change5dPercent": -0.86, "marketCap": 20254211666, "volume": 1163104, "avgVolume10d": 4326350, "avgVolume60d": 3731748, "avgVolume90d": 4250471, "avgTradingValue": 174299860, "sma10": 49.51, "sma20": 47.8, "sma30": 47.45, "sma50": 46.52, "sma100": 45.98, "sma200": 40.17, "sector": "", "indices": []}, {"ticker": "VTRS", "name": "Viatris Inc.", "price": 16.54, "change": -0.72, "changePercent": -4.17, "change5dPercent": -3.67, "marketCap": 19255877956, "volume": 3154565, "avgVolume10d": 15823336, "avgVolume60d": 11364141, "avgVolume90d": 10744710, "avgTradingValue": 212080810, "sma10": 16.65, "sma20": 15.73, "sma30": 15.07, "sma50": 14.47, "sma100": 14.13, "sma200": 12.14, "sector": "Healthcare", "indices": []}, {"ticker": "WES", "name": "Western Midstream Partners, LP", "price": 46.79, "change": 0.92, "changePercent": 2.01, "change5dPercent": 7.59, "marketCap": 18432905019, "volume": 1399963, "avgVolume10d": 1593126, "avgVolume60d": 1538617, "avgVolume90d": 1500045, "avgTradingValue": 74194391, "sma10": 43.99, "sma20": 42.34, "sma30": 41.57, "sma50": 41.13, "sma100": 40.43, "sma200": 38.42, "sector": "Energy", "indices": []}, {"ticker": "ROKU", "name": "Roku, Inc.", "price": 123.71, "change": -2.14, "changePercent": -1.7, "change5dPercent": -4.49, "marketCap": 18262332536, "volume": 724481, "avgVolume10d": 2279978, "avgVolume60d": 2816874, "avgVolume90d": 3218709, "avgTradingValue": 335317361, "sma10": 126.56, "sma20": 121.32, "sma30": 115.79, "sma50": 107.57, "sma100": 103.81, "sma200": 100.59, "sector": "Communication Services", "indices": []}, {"ticker": "AMKR", "name": "AMKR", "price": 70.75, "change": -1.34, "changePercent": -1.86, "change5dPercent": -7.65, "marketCap": 17512193774, "volume": 1538076, "avgVolume10d": 4387457, "avgVolume60d": 4175624, "avgVolume90d": 4440561, "avgTradingValue": 378364751, "sma10": 74.14, "sma20": 73.13, "sma30": 67.82, "sma50": 58.77, "sma100": 53.28, "sma200": 41.95, "sector": "", "indices": []}, {"ticker": "TTMI", "name": "TTM Technologies, Inc.", "price": 165.48, "change": -6.39, "changePercent": -3.72, "change5dPercent": 5.19, "marketCap": 17239109794, "volume": 718537, "avgVolume10d": 2113673, "avgVolume60d": 2012937, "avgVolume90d": 2429983, "avgTradingValue": 363290156, "sma10": 162.53, "sma20": 151.08, "sma30": 138.51, "sma50": 121.58, "sma100": 106.52, "sma200": 81.82, "sector": "Technology", "indices": []}, {"ticker": "OVV", "name": "Ovintiv Inc. (DE)", "price": 59.7, "change": 1.4, "changePercent": 2.4, "change5dPercent": 3.23, "marketCap": 16825988734, "volume": 1707777, "avgVolume10d": 4720047, "avgVolume60d": 4530339, "avgVolume90d": 4667246, "avgTradingValue": 234118296, "sma10": 59.5, "sma20": 58.52, "sma30": 57.81, "sma50": 57.47, "sma100": 50.5, "sma200": 44.81, "sector": "Energy", "indices": []}, {"ticker": "LSCC", "name": "Lattice Semiconductor Corporati", "price": 120.7, "change": -4.15, "changePercent": -3.32, "change5dPercent": -5.1, "marketCap": 16577950697, "volume": 1024164, "avgVolume10d": 2784836, "avgVolume60d": 1953092, "avgVolume90d": 2035897, "avgTradingValue": 311307753, "sma10": 124.57, "sma20": 121.5, "sma30": 116.63, "sma50": 106.7, "sma100": 96.87, "sma200": 82.51, "sector": "Technology", "indices": []}, {"ticker": "BEN", "name": "BEN", "price": 31.78, "change": -0.56, "changePercent": -1.75, "change5dPercent": 2.37, "marketCap": 16503676384, "volume": 1041906, "avgVolume10d": 4157730, "avgVolume60d": 5205665, "avgVolume90d": 5444207, "avgTradingValue": 158928021, "sma10": 31.23, "sma20": 29.75, "sma30": 28.32, "sma50": 26.5, "sma100": 26.09, "sma200": 24.47, "sector": "", "indices": []}, {"ticker": "PAA", "name": "Plains All American Pipeline, L", "price": 22.75, "change": 0.27, "changePercent": 1.18, "change5dPercent": 4.72, "marketCap": 16047318744, "volume": 995480, "avgVolume10d": 3257278, "avgVolume60d": 3416039, "avgVolume90d": 3580379, "avgTradingValue": 72164903, "sma10": 22.23, "sma20": 21.85, "sma30": 21.67, "sma50": 21.57, "sma100": 20.23, "sma200": 18.25, "sector": "Energy", "indices": []}, {"ticker": "AAOI", "name": "AAOI", "price": 189.26, "change": -14.31, "changePercent": -7.03, "change5dPercent": 27.07, "marketCap": 15193959850, "volume": 5373679, "avgVolume10d": 13142997, "avgVolume60d": 12418981, "avgVolume90d": 9953237, "avgTradingValue": 1957659236, "sma10": 182.77, "sma20": 168.74, "sma30": 159.18, "sma50": 135.49, "sma100": 91.24, "sma200": 59.17, "sector": "", "indices": []}, {"ticker": "PL", "name": "Planet Labs PBC", "price": 41.97, "change": -1.07, "changePercent": -2.47, "change5dPercent": 7.52, "marketCap": 14868724572, "volume": 3984919, "avgVolume10d": 8988491, "avgVolume60d": 12986153, "avgVolume90d": 12999637, "avgTradingValue": 347918952, "sma10": 39.79, "sma20": 38.25, "sma30": 37.39, "sma50": 33.95, "sma100": 28.88, "sma200": 20.1, "sector": "Industrials", "indices": []}, {"ticker": "HST", "name": "Host Hotels & Resorts, Inc.", "price": 21.31, "change": -0.24, "changePercent": -1.09, "change5dPercent": -4.33, "marketCap": 14611898833, "volume": 2339809, "avgVolume10d": 7891580, "avgVolume60d": 8661911, "avgVolume90d": 8623092, "avgTradingValue": 150741893, "sma10": 21.57, "sma20": 21.31, "sma30": 20.92, "sma50": 20.1, "sma100": 19.43, "sma200": 17.91, "sector": "Real Estate", "indices": []}, {"ticker": "OHI", "name": "Omega Healthcare Investors, Inc", "price": 47.49, "change": -0.44, "changePercent": -0.92, "change5dPercent": 0.64, "marketCap": 14172397225, "volume": 1136191, "avgVolume10d": 2094069, "avgVolume60d": 2037041, "avgVolume90d": 2085464, "avgTradingValue": 105323483, "sma10": 46.98, "sma20": 46.41, "sma30": 46.0, "sma50": 45.79, "sma100": 44.97, "sma200": 42.83, "sector": "Real Estate", "indices": []}, {"ticker": "HAS", "name": "Hasbro, Inc.", "price": 95.02, "change": -0.63, "changePercent": -0.66, "change5dPercent": -2.82, "marketCap": 13443030949, "volume": 559194, "avgVolume10d": 1575019, "avgVolume60d": 1695819, "avgVolume90d": 1861803, "avgTradingValue": 164068457, "sma10": 95.58, "sma20": 94.99, "sma30": 94.27, "sma50": 93.53, "sma100": 92.55, "sma200": 84.69, "sector": "Consumer Cyclical", "indices": []}, {"ticker": "SMTC", "name": "Semtech Corporation", "price": 137.96, "change": -3.2, "changePercent": -2.27, "change5dPercent": 13.26, "marketCap": 12820935870, "volume": 1018176, "avgVolume10d": 2469887, "avgVolume60d": 2452446, "avgVolume90d": 2134537, "avgTradingValue": 292607400, "sma10": 127.01, "sma20": 115.24, "sma30": 107.23, "sma50": 96.2, "sma100": 89.24, "sma200": 76.88, "sector": "Technology", "indices": []}, {"ticker": "DINO", "name": "DINO", "price": 69.84, "change": 1.13, "changePercent": 1.64, "change5dPercent": -2.91, "marketCap": 12586830956, "volume": 682158, "avgVolume10d": 2555695, "avgVolume60d": 2801964, "avgVolume90d": 2801466, "avgTradingValue": 162557213, "sma10": 70.99, "sma20": 66.46, "sma30": 63.68, "sma50": 61.7, "sma100": 56.12, "sma200": 52.82, "sector": "", "indices": []}, {"ticker": "EXEL", "name": "Exelixis, Inc.", "price": 49.67, "change": -1.43, "changePercent": -2.8, "change5dPercent": 3.14, "marketCap": 12482293383, "volume": 746753, "avgVolume10d": 3175265, "avgVolume60d": 2793010, "avgVolume90d": 2753015, "avgTradingValue": 134715739, "sma10": 48.29, "sma20": 46.63, "sma30": 45.96, "sma50": 44.35, "sma100": 44.08, "sma200": 41.93, "sector": "Healthcare", "indices": []}, {"ticker": "VICR", "name": "Vicor Corporation", "price": 269.63, "change": -20.91, "changePercent": -7.2, "change5dPercent": 5.13, "marketCap": 12283504797, "volume": 560703, "avgVolume10d": 955420, "avgVolume60d": 939800, "avgVolume90d": 813175, "avgTradingValue": 278534849, "sma10": 279.01, "sma20": 268.57, "sma30": 240.97, "sma50": 213.05, "sma100": 183.99, "sma200": 126.0, "sector": "Technology", "indices": []}, {"ticker": "VIAV", "name": "Viavi Solutions Inc.", "price": 51.03, "change": -2.08, "changePercent": -3.93, "change5dPercent": -0.36, "marketCap": 11935149423, "volume": 2153669, "avgVolume10d": 5395706, "avgVolume60d": 6382766, "avgVolume90d": 5926862, "avgTradingValue": 325019858, "sma10": 52.78, "sma20": 49.81, "sma30": 46.78, "sma50": 41.08, "sma100": 32.15, "sma200": 23.05, "sector": "Technology", "indices": []}, {"ticker": "HUT", "name": "Hut 8 Corp.", "price": 101.36, "change": -8.01, "changePercent": -7.32, "change5dPercent": 2.95, "marketCap": 11457577077, "volume": 2307039, "avgVolume10d": 6299403, "avgVolume60d": 4868157, "avgVolume90d": 4959698, "avgTradingValue": 472424785, "sma10": 99.57, "sma20": 87.96, "sma30": 80.36, "sma50": 67.97, "sma100": 61.52, "sma200": 49.04, "sector": "Financial Services", "indices": []}, {"ticker": "BTSG", "name": "BTSG", "price": 57.47, "change": -0.93, "changePercent": -1.59, "change5dPercent": 4.81, "marketCap": 11153216542, "volume": 1065059, "avgVolume10d": 2602105, "avgVolume60d": 2956742, "avgVolume90d": 2495108, "avgTradingValue": 152300865, "sma10": 54.84, "sma20": 51.48, "sma30": 49.52, "sma50": 46.46, "sma100": 42.92, "sma200": 36.13, "sector": "", "indices": []}, {"ticker": "WULF", "name": "TeraWulf Inc.", "price": 22.1, "change": -2.07, "changePercent": -8.54, "change5dPercent": -5.49, "marketCap": 10995869657, "volume": 14002628, "avgVolume10d": 28420652, "avgVolume60d": 31081772, "avgVolume90d": 31615220, "avgTradingValue": 654135177, "sma10": 23.45, "sma20": 22.05, "sma30": 20.97, "sma50": 18.62, "sma100": 16.46, "sma200": 14.02, "sector": "Financial Services", "indices": []}, {"ticker": "ARWR", "name": "ARWR", "price": 77.58, "change": -2.11, "changePercent": -2.64, "change5dPercent": 6.73, "marketCap": 10915010256, "volume": 516699, "avgVolume10d": 1774709, "avgVolume60d": 2102969, "avgVolume90d": 2521878, "avgTradingValue": 128828952, "sma10": 77.3, "sma20": 74.91, "sma30": 71.84, "sma50": 66.49, "sma100": 66.23, "sma200": 51.64, "sector": "", "indices": []}, {"ticker": "CGNX", "name": "CGNX", "price": 64.23, "change": -1.86, "changePercent": -2.81, "change5dPercent": -2.18, "marketCap": 10719077448, "volume": 723363, "avgVolume10d": 3660276, "avgVolume60d": 2195996, "avgVolume90d": 2247300, "avgTradingValue": 160590657, "sma10": 63.59, "sma20": 59.06, "sma30": 57.29, "sma50": 54.2, "sma100": 49.17, "sma200": 45.61, "sector": "", "indices": []}, {"ticker": "GSAT", "name": "Globalstar, Inc.", "price": 81.63, "change": -0.45, "changePercent": -0.55, "change5dPercent": -0.56, "marketCap": 10514971839, "volume": 527148, "avgVolume10d": 1106394, "avgVolume60d": 1376835, "avgVolume90d": 1125037, "avgTradingValue": 105691047, "sma10": 81.98, "sma20": 81.69, "sma30": 79.83, "sma50": 72.54, "sma100": 67.01, "sma200": 55.43, "sector": "Communication Services", "indices": []}, {"ticker": "CYTK", "name": "CYTK", "price": 75.88, "change": -2.76, "changePercent": -3.51, "change5dPercent": -1.34, "marketCap": 10270027329, "volume": 846262, "avgVolume10d": 5237736, "avgVolume60d": 2497886, "avgVolume90d": 2228529, "avgTradingValue": 255093896, "sma10": 75.03, "sma20": 69.42, "sma30": 68.16, "sma50": 65.94, "sma100": 64.98, "sma200": 59.53, "sector": "", "indices": []}, {"ticker": "DAR", "name": "DAR", "price": 62.58, "change": -0.2, "changePercent": -0.32, "change5dPercent": -0.86, "marketCap": 9948852681, "volume": 732385, "avgVolume10d": 2368318, "avgVolume60d": 2998186, "avgVolume90d": 2892752, "avgTradingValue": 162053878, "sma10": 63.26, "sma20": 62.29, "sma30": 61.89, "sma50": 60.04, "sma100": 52.37, "sma200": 42.64, "sector": "", "indices": []}, {"ticker": "VNOM", "name": "Viper Energy, Inc.", "price": 48.5, "change": 0.81, "changePercent": 1.71, "change5dPercent": 5.13, "marketCap": 9411659449, "volume": 674134, "avgVolume10d": 1553403, "avgVolume60d": 3009238, "avgVolume90d": 2784018, "avgTradingValue": 69274023, "sma10": 47.71, "sma20": 47.53, "sma30": 46.76, "sma50": 46.22, "sma100": 43.14, "sma200": 39.85, "sector": "Energy", "indices": []}, {"ticker": "RIOT", "name": "Riot Platforms, Inc.", "price": 23.3, "change": -1.32, "changePercent": -5.36, "change5dPercent": -3.24, "marketCap": 8818486568, "volume": 6914736, "avgVolume10d": 19261763, "avgVolume60d": 18310880, "avgVolume90d": 19232271, "avgTradingValue": 402465522, "sma10": 23.36, "sma20": 20.55, "sma30": 19.2, "sma50": 17.08, "sma100": 16.31, "sma200": 16.22, "sector": "Financial Services", "indices": []}, {"ticker": "MXL", "name": "MaxLinear, Inc", "price": 92.78, "change": 4.0, "changePercent": 4.51, "change5dPercent": -7.06, "marketCap": 8416872662, "volume": 4053866, "avgVolume10d": 5247876, "avgVolume60d": 3441092, "avgVolume90d": 2701626, "avgTradingValue": 532166335, "sma10": 88.67, "sma20": 69.99, "sma30": 53.69, "sma50": 38.98, "sma100": 28.66, "sma200": 22.33, "sector": "Technology", "indices": []}, {"ticker": "CIFR", "name": "CIFR", "price": 20.28, "change": -2.01, "changePercent": -9.02, "change5dPercent": -1.31, "marketCap": 8262794091, "volume": 12560931, "avgVolume10d": 30334353, "avgVolume60d": 25922673, "avgVolume90d": 28115588, "avgTradingValue": 521532170, "sma10": 20.73, "sma20": 19.4, "sma30": 18.49, "sma50": 16.72, "sma100": 16.55, "sma200": 15.16, "sector": "", "indices": []}, {"ticker": "AXTI", "name": "AXTI", "price": 121.73, "change": 6.75, "changePercent": 5.87, "change5dPercent": 4.61, "marketCap": 7987516294, "volume": 5275040, "avgVolume10d": 9930214, "avgVolume60d": 12114162, "avgVolume90d": 10532658, "avgTradingValue": 1122107508, "sma10": 115.05, "sma20": 96.39, "sma30": 85.22, "sma50": 71.96, "sma100": 47.86, "sma200": 27.16, "sector": "", "indices": []}, {"ticker": "JHG", "name": "Janus Henderson Group plc", "price": 51.7, "change": 0.0, "changePercent": 0.0, "change5dPercent": 0.02, "marketCap": 7967249600, "volume": 632611, "avgVolume10d": 2734811, "avgVolume60d": 3146395, "avgVolume90d": 2711404, "avgTradingValue": 111875634, "sma10": 51.68, "sma20": 51.62, "sma30": 51.59, "sma50": 51.4, "sma100": 50.04, "sma200": 46.82, "sector": "Financial Services", "indices": []}, {"ticker": "ALGM", "name": "ALGM", "price": 42.78, "change": -2.19, "changePercent": -4.87, "change5dPercent": -12.6, "marketCap": 7928596496, "volume": 1196071, "avgVolume10d": 2895237, "avgVolume60d": 2111804, "avgVolume90d": 2416186, "avgTradingValue": 119891895, "sma10": 47.54, "sma20": 45.67, "sma30": 42.72, "sma50": 38.29, "sma100": 36.38, "sma200": 32.68, "sector": "", "indices": []}, {"ticker": "CORZ", "name": "CORZ", "price": 23.73, "change": -1.19, "changePercent": -4.78, "change5dPercent": 3.53, "marketCap": 7543417833, "volume": 4634078, "avgVolume10d": 18425867, "avgVolume60d": 13765056, "avgVolume90d": 12834705, "avgTradingValue": 374370862, "sma10": 23.16, "sma20": 21.81, "sma30": 20.63, "sma50": 18.75, "sma100": 17.97, "sma200": 17.24, "sector": "", "indices": []}, {"ticker": "KGS", "name": "Kodiak Gas Services, Inc.", "price": 73.66, "change": -0.57, "changePercent": -0.77, "change5dPercent": 5.75, "marketCap": 6546863241, "volume": 1583024, "avgVolume10d": 2419002, "avgVolume60d": 1471955, "avgVolume90d": 1528615, "avgTradingValue": 123886872, "sma10": 72.46, "sma20": 69.09, "sma30": 66.42, "sma50": 62.62, "sma100": 53.14, "sma200": 43.68, "sector": "Energy", "indices": []}, {"ticker": "CELC", "name": "CELC", "price": 133.32, "change": -1.4, "changePercent": -1.04, "change5dPercent": 1.72, "marketCap": 6451496071, "volume": 565797, "avgVolume10d": 1489669, "avgVolume60d": 870588, "avgVolume90d": 837223, "avgTradingValue": 158331097, "sma10": 133.07, "sma20": 127.28, "sma30": 124.89, "sma50": 119.62, "sma100": 113.33, "sma200": 90.43, "sector": "", "indices": []}, {"ticker": "TGTX", "name": "TG Therapeutics, Inc.", "price": 39.6, "change": -1.19, "changePercent": -2.92, "change5dPercent": -7.61, "marketCap": 6101146010, "volume": 685869, "avgVolume10d": 2823456, "avgVolume60d": 2138111, "avgVolume90d": 2111657, "avgTradingValue": 91926880, "sma10": 40.84, "sma20": 38.23, "sma30": 36.9, "sma50": 34.33, "sma100": 32.06, "sma200": 32.06, "sector": "Healthcare", "indices": []}, {"ticker": "GTX", "name": "Garrett Motion Inc.", "price": 31.28, "change": -0.59, "changePercent": -1.85, "change5dPercent": 7.86, "marketCap": 5872103496, "volume": 824735, "avgVolume10d": 3366693, "avgVolume60d": 2455310, "avgVolume90d": 2504961, "avgTradingValue": 78808981, "sma10": 28.73, "sma20": 25.11, "sma30": 23.11, "sma50": 21.04, "sma100": 19.88, "sma200": 17.18, "sector": "Consumer Cyclical", "indices": []}, {"ticker": "LUNR", "name": "Intuitive Machines, Inc.", "price": 34.35, "change": -2.17, "changePercent": -5.94, "change5dPercent": 18.57, "marketCap": 5512285549, "volume": 7929294, "avgVolume10d": 12852039, "avgVolume60d": 13596896, "avgVolume90d": 12685226, "avgTradingValue": 348966963, "sma10": 30.06, "sma20": 28.28, "sma30": 26.9, "sma50": 23.6, "sma100": 20.89, "sma200": 15.62, "sector": "Industrials", "indices": []}, {"ticker": "USAR", "name": "USA Rare Earth, Inc.", "price": 24.32, "change": -0.51, "changePercent": -2.05, "change5dPercent": -9.79, "marketCap": 5442040724, "volume": 7349478, "avgVolume10d": 17107927, "avgVolume60d": 15225512, "avgVolume90d": 18812943, "avgTradingValue": 508281256, "sma10": 26.14, "sma20": 24.89, "sma30": 22.26, "sma50": 20.37, "sma100": 19.75, "sma200": 18.82, "sector": "Basic Materials", "indices": []}, {"ticker": "LBRT", "name": "Liberty Energy Inc.", "price": 32.81, "change": -0.54, "changePercent": -1.62, "change5dPercent": -0.91, "marketCap": 5358389994, "volume": 1474275, "avgVolume10d": 3072817, "avgVolume60d": 4160391, "avgVolume90d": 4424086, "avgTradingValue": 127290890, "sma10": 33.12, "sma20": 32.34, "sma30": 30.77, "sma50": 30.25, "sma100": 26.6, "sma200": 20.36, "sector": "Energy", "indices": []}, {"ticker": "LQDA", "name": "Liquidia Corporation", "price": 57.15, "change": -2.15, "changePercent": -3.63, "change5dPercent": 35.11, "marketCap": 5085353463, "volume": 881988, "avgVolume10d": 2108848, "avgVolume60d": 1449366, "avgVolume90d": 1688110, "avgTradingValue": 70588852, "sma10": 48.91, "sma20": 43.27, "sma30": 41.87, "sma50": 39.79, "sma100": 38.39, "sma200": 32.42, "sector": "Healthcare", "indices": []}, {"ticker": "RELY", "name": "Remitly Global, Inc.", "price": 22.68, "change": -0.63, "changePercent": -2.7, "change5dPercent": -5.62, "marketCap": 4773419676, "volume": 1427852, "avgVolume10d": 8713425, "avgVolume60d": 4339892, "avgVolume90d": 4186518, "avgTradingValue": 134366935, "sma10": 23.6, "sma20": 22.47, "sma30": 20.86, "sma50": 18.89, "sma100": 16.6, "sma200": 16.34, "sector": "Technology", "indices": []}, {"ticker": "NVTS", "name": "Navitas Semiconductor Corporati", "price": 20.32, "change": -2.0, "changePercent": -8.96, "change5dPercent": 11.65, "marketCap": 4751388646, "volume": 18714309, "avgVolume10d": 38451970, "avgVolume60d": 28455128, "avgVolume90d": 26652958, "avgTradingValue": 756153106, "sma10": 18.98, "sma20": 17.77, "sma30": 15.2, "sma50": 12.77, "sma100": 10.87, "sma200": 9.65, "sector": "Technology", "indices": []}, {"ticker": "PTEN", "name": "Patterson-UTI Energy, Inc.", "price": 12.22, "change": 0.1, "changePercent": 0.78, "change5dPercent": 6.96, "marketCap": 4637029689, "volume": 1863714, "avgVolume10d": 6181551, "avgVolume60d": 10138908, "avgVolume90d": 10550836, "avgTradingValue": 95818286, "sma10": 11.94, "sma20": 11.64, "sma30": 11.18, "sma50": 10.89, "sma100": 9.16, "sma200": 7.4, "sector": "Energy", "indices": []}, {"ticker": "IRDM", "name": "Iridium Communications Inc", "price": 41.38, "change": -2.05, "changePercent": -4.71, "change5dPercent": -0.18, "marketCap": 4384000921, "volume": 676049, "avgVolume10d": 1860794, "avgVolume60d": 2258720, "avgVolume90d": 2344370, "avgTradingValue": 94015102, "sma10": 41.41, "sma20": 40.43, "sma30": 39.1, "sma50": 34.06, "sma100": 27.23, "sma200": 23.23, "sector": "Communication Services", "indices": []}, {"ticker": "CRGY", "name": "CRGY", "price": 12.93, "change": 0.32, "changePercent": 2.54, "change5dPercent": 4.27, "marketCap": 4275107223, "volume": 3039393, "avgVolume10d": 8032219, "avgVolume60d": 8706614, "avgVolume90d": 7756373, "avgTradingValue": 88888099, "sma10": 12.89, "sma20": 12.88, "sma30": 12.82, "sma50": 12.73, "sma100": 11.03, "sma200": 9.9, "sector": "", "indices": []}, {"ticker": "LASR", "name": "nLIGHT, Inc.", "price": 74.92, "change": -6.41, "changePercent": -7.88, "change5dPercent": 1.37, "marketCap": 4241652856, "volume": 567016, "avgVolume10d": 1592671, "avgVolume60d": 1759768, "avgVolume90d": 1588900, "avgTradingValue": 93612784, "sma10": 75.32, "sma20": 73.02, "sma30": 70.26, "sma50": 67.97, "sma100": 58.03, "sma200": 44.25, "sector": "Technology", "indices": []}, {"ticker": "TPH", "name": "Tri Pointe Homes, Inc.", "price": 46.95, "change": -0.02, "changePercent": -0.04, "change5dPercent": 0.0, "marketCap": 3998444306, "volume": 10693114, "avgVolume10d": 2626535, "avgVolume60d": 2768392, "avgVolume90d": 2458738, "avgTradingValue": 106481436, "sma10": 46.91, "sma20": 46.89, "sma30": 46.84, "sma50": 46.71, "sma100": 41.75, "sma200": 37.57, "sector": "Consumer Cyclical", "indices": []}, {"ticker": "CPRX", "name": "CPRX", "price": 31.15, "change": -0.01, "changePercent": -0.05, "change5dPercent": -0.02, "marketCap": 3810944016, "volume": 1482172, "avgVolume10d": 3920007, "avgVolume60d": 1919417, "avgVolume90d": 1689403, "avgTradingValue": 95724008, "sma10": 30.84, "sma20": 29.25, "sma30": 28.01, "sma50": 26.31, "sma100": 25.11, "sma200": 23.19, "sector": "", "indices": []}, {"ticker": "SEDG", "name": "SolarEdge Technologies, Inc.", "price": 59.77, "change": 9.53, "changePercent": 18.98, "change5dPercent": 44.73, "marketCap": 3642706236, "volume": 7073907, "avgVolume10d": 4644590, "avgVolume60d": 3834553, "avgVolume90d": 3567144, "avgTradingValue": 176053641, "sma10": 44.17, "sma20": 43.84, "sma30": 43.14, "sma50": 43.63, "sma100": 38.99, "sma200": 36.36, "sector": "Technology", "indices": []}, {"ticker": "VECO", "name": "Veeco Instruments Inc.", "price": 57.6, "change": -1.91, "changePercent": -3.21, "change5dPercent": -3.06, "marketCap": 3519800968, "volume": 572037, "avgVolume10d": 2161383, "avgVolume60d": 1376888, "avgVolume90d": 1182613, "avgTradingValue": 102108079, "sma10": 57.97, "sma20": 53.6, "sma30": 48.96, "sma50": 42.41, "sma100": 36.86, "sma200": 32.3, "sector": "Technology", "indices": []}, {"ticker": "RNG", "name": "Ringcentral, Inc.", "price": 41.11, "change": 1.76, "changePercent": 4.47, "change5dPercent": -9.91, "marketCap": 3444911605, "volume": 631542, "avgVolume10d": 2453384, "avgVolume60d": 2234970, "avgVolume90d": 2309420, "avgTradingValue": 85723542, "sma10": 43.74, "sma20": 42.27, "sma30": 40.76, "sma50": 39.66, "sma100": 34.67, "sma200": 31.81, "sector": "Technology", "indices": []}, {"ticker": "HIMX", "name": "Himax Technologies, Inc.", "price": 19.24, "change": -1.44, "changePercent": -6.96, "change5dPercent": 8.15, "marketCap": 3366420007, "volume": 3233517, "avgVolume10d": 8717131, "avgVolume60d": 4301855, "avgVolume90d": 3228475, "avgTradingValue": 93790231, "sma10": 17.02, "sma20": 14.27, "sma30": 12.73, "sma50": 11.09, "sma100": 9.56, "sma200": 8.96, "sector": "Technology", "indices": []}, {"ticker": "AEHR", "name": "AEHR", "price": 99.68, "change": -6.66, "changePercent": -6.26, "change5dPercent": 2.52, "marketCap": 3132115090, "volume": 1262676, "avgVolume10d": 2770057, "avgVolume60d": 2939311, "avgVolume90d": 2430885, "avgTradingValue": 286104143, "sma10": 97.26, "sma20": 94.08, "sma30": 85.68, "sma50": 66.43, "sma100": 47.55, "sma200": 35.95, "sector": "", "indices": []}], "totalUniverse": 5780, "totalPassing": 138, "lastUpdated": "2026-05-15T17:11:33.312092"}